embuild/__init__.py
embuild/bibtex.py
embuild/constants.py
embuild/protocols.conf
embuild/protocols/__init__.py
embuild/protocols/protocol_embuild_assemble.py
embuild/protocols/protocol_embuild_main_chain_prediction.py
embuild/protocols/protocol_embuild_quality_check.py
embuild/tests/__init__.py
embuild/tests/test_protocol_assemble.py
embuild/tests/test_protocol_main_chain_prediction.py
embuild/tests/test_protocol_quality_check.py
embuild/viewers/__init__.py
scipion_em_embuild-1.0.4.dist-info/LICENSE
scipion_em_embuild-1.0.4.dist-info/METADATA
scipion_em_embuild-1.0.4.dist-info/WHEEL
scipion_em_embuild-1.0.4.dist-info/entry_points.txt
scipion_em_embuild-1.0.4.dist-info/top_level.txt
scipion_em_embuild-1.0.4.dist-info/RECORD
