Metadata-Version: 2.1
Name: scipion-em-embuild
Version: 1.0.4
Summary: EMBuild: Model building of protein complexes from intermediate-resolution cryo-EM maps with deep learning-guided automatic assembly
Home-page: https://github.com/scipion-em/scipion-em-embuild
Author: Jiahua He, Tao Li, Yunior C. Fonseca Reyna, Sheng-You Huang
Author-email: d201880053@hust.edu.cn, d202280084@hust.edu.cn, cfonseca@cnb.csic.es, huangsy@hust.edu.cn
License: UNKNOWN
Project-URL: Bug Reports, https://github.com/scipion-em/scipion-em-embuild/issues
Project-URL: Source, https://github.com/scipion-em/scipion-em-embuild/
Keywords: scipion electron-microscopy cryo-em structural-biology image-processing scipion-3.0 embuild
Platform: UNKNOWN
Classifier: Development Status :: 3 - Alpha
Classifier: License :: OSI Approved :: GNU General Public License v3 (GPLv3)
Classifier: Programming Language :: Python :: 3.8
Requires-Dist: scipion-em
Requires-Dist: scipion-pyworkflow
